unitas/__init__.py
unitas/convert.py
unitas/exporter.py
unitas/merger.py
unitas/model.py
unitas/parser.py
unitas/unitas.py
unitas/utils.py
unitas/webserver.py
unitas/resources/__init__.py
unitas/resources/index.html
unitas/resources/static/css/styles.css
unitas/resources/static/js/analysis.js
unitas/resources/static/js/app.js
unitas/resources/static/js/auto-loader.js
unitas/resources/static/js/dataHandlers.js
unitas/resources/static/js/filters.js
unitas/resources/static/js/networkGraph.js
unitas/resources/static/js/tableRenderers.js
unitas-1.2.6.dist-info/licenses/LICENSE
unitas-1.2.6.dist-info/METADATA
unitas-1.2.6.dist-info/WHEEL
unitas-1.2.6.dist-info/entry_points.txt
unitas-1.2.6.dist-info/top_level.txt
unitas-1.2.6.dist-info/RECORD
