Metadata-Version: 2.4
Name: unitas
Version: 1.2.6
Summary: unitas - A tool to help with nessus and nmap scans
Author-email: f0rw4rd <f0rw4rd@users.noreply.github.com>
License: GPL-3.0
Classifier: Programming Language :: Python :: 3
Classifier: License :: OSI Approved :: GNU General Public License v3 (GPLv3)
Classifier: Operating System :: OS Independent
Classifier: Topic :: Security
Classifier: Topic :: System :: Networking :: Monitoring
Requires-Python: >=3.8
License-File: LICENSE
Requires-Dist: requests
Requires-Dist: manuf2
Dynamic: license-file
